<?xml version="1.0" encoding="UTF-8"?>
<beans xmlns="http://www.springframework.org/schema/beans"
	xmlns:xsi="http://www.w3.org/2001/XMLSchema-instance"

	xsi:schemaLocation="http://www.springframework.org/schema/beans
        http://www.springframework.org/schema/beans/spring-beans.xsd">

	<!-- email 인증 관련 -->
	<bean id="mailSender"
		class="org.springframework.mail.javamail.JavaMailSenderImpl">
		<property name="host" value="smtp.naver.com" />
		<property name="port" value="465" />
		<property name="username" value="ywj9811@naver.com" /> <!-- "이메일 주소" -->
		<property name="password" value="hailag1124!" /> <!-- "비밀번호" -->
		<property name="javaMailProperties">
			<props>
				<prop key="mail.smtp.auth">true</prop>
				<prop key="mail.smtp.starttls.enable">true</prop>
				<prop key="mail.smtps.checkserveridentity">true</prop>
				<prop key="mail.smtp.ssl.enable">true</prop>
				<prop key="mail.smtps.ssl.trust">*</prop>
				<prop key="mail.debug">true</prop>
				<prop key="mail.smtp.socketFactory.class">javax.net.ssl.SSLSocketFactory</prop>
			</props>
		</property>
	</bean>
</beans>